commons_metrics/__init__.py
commons_metrics/azure_devops_client.py
commons_metrics/cache_manager.py
commons_metrics/commons_repos_client.py
commons_metrics/database.py
commons_metrics/date_utils.py
commons_metrics/github_api_client.py
commons_metrics/repositories.py
commons_metrics/s3_file_manager.py
commons_metrics/text_simplifier.py
commons_metrics/update_design_components.py
commons_metrics/util.py
commons_metrics/variable_finder.py
commons_metrics-0.0.27.dist-info/licenses/LICENSE
commons_metrics-0.0.27.dist-info/METADATA
commons_metrics-0.0.27.dist-info/WHEEL
commons_metrics-0.0.27.dist-info/top_level.txt
commons_metrics-0.0.27.dist-info/RECORD
