Metadata-Version: 2.4
Name: commons_metrics
Version: 0.0.27
Summary: A simple library for basic statistical calculations
Author: Bancolombia
Author-email: omar.david.pino@email.com
License: MIT
Requires-Python: >=3.7
License-File: LICENSE
Requires-Dist: boto3
Dynamic: author
Dynamic: author-email
Dynamic: license
Dynamic: license-file
Dynamic: requires-dist
Dynamic: requires-python
Dynamic: summary
